httprequestor/__init__.py
httprequestor/httprequestor.py
httprequestor-0.1.2.dist-info/licenses/LICENSE
httprequestor-0.1.2.dist-info/METADATA
httprequestor-0.1.2.dist-info/WHEEL
httprequestor-0.1.2.dist-info/top_level.txt
httprequestor-0.1.2.dist-info/RECORD
