Metadata-Version: 2.4
Name: httprequestor
Version: 0.1.2
License-File: LICENSE
Dynamic: description
Dynamic: description-content-type
Dynamic: license-file
